ansible_inventory_manage/__init__.py
ansible_inventory_manage/inventory.py
ansible_inventory_manage-0.0.2.dist-info/METADATA
ansible_inventory_manage-0.0.2.dist-info/RECORD
ansible_inventory_manage-0.0.2.dist-info/WHEEL
ansible_inventory_manage-0.0.2.dist-info/top_level.txt
