Metadata-Version: 2.1
Name: ansible-inventory-manage
Version: 0.0.2
Summary: Ansible Inventory CRUD library
Home-page: https://github.com/evrardjp/ansible-inventory-manage
Author: Jean-Philippe Evrard
Author-email: jean-philippe@evrard.me
License: Apache License 2.0
Platform: UNKNOWN
Classifier: Development Status :: 2 - Pre-Alpha
Classifier: Environment :: Console
Classifier: Intended Audience :: Information Technology
Classifier: Intended Audience :: System Administrators
Classifier: License :: OSI Approved :: Apache Software License
Classifier: Operating System :: POSIX :: Linux
Classifier: Programming Language :: Python
Classifier: Programming Language :: Python :: 2
Classifier: Programming Language :: Python :: 2.7
Classifier: Programming Language :: Python :: 3
Classifier: Programming Language :: Python :: 3.5
Classifier: Programming Language :: Python :: 3.6
Requires-Dist: future
